AUTHORS.rst
CONTRIBUTING.rst
LICENSE
MANIFEST.in
README.rst
requirements.txt
setup.cfg
setup.py
versioneer.py
docs/Makefile
docs/make.bat
docs/source/conf.py
docs/source/index.rst
motor_watch/__init__.py
motor_watch/_version.py
motor_watch/status.py
motor_watch/utils.py
motor_watch.egg-info/PKG-INFO
motor_watch.egg-info/SOURCES.txt
motor_watch.egg-info/dependency_links.txt
motor_watch.egg-info/entry_points.txt
motor_watch.egg-info/requires.txt
motor_watch.egg-info/top_level.txt