Metadata-Version: 1.1
Name: motor-watch
Version: 0.0.0
Summary: Track motor motion through Status objects
Home-page: https://github.com/pcdshub/motor_watch
Author: SLAC National Accelerator Laboratory
Author-email: UNKNOWN
License: BSD
Platform: UNKNOWN
Classifier: Development Status :: 2 - Pre-Alpha
Classifier: Natural Language :: English
Classifier: Programming Language :: Python :: 3
